<description><call id="a0" endpoint="move"><parameters><label>Move to coords</label><method>:post</method><arguments><v1>-0.004698341281416118</v1><v2>0.5281156079500122</v2><v3>0.24377560051671007</v3><v4>-2.7162683339137677</v4><v5>1.4792509145658843</v5><v6>0.19389963763344725</v6></arguments></parameters><annotations><_generic /><_timing><_timing_weight /><_timing_avg /><explanations /></_timing><_shifting><_shifting_type>Duration</_shifting_type></_shifting><_context_data_analysis><probes /><ips /></_context_data_analysis><report><url /></report><_notes><_notes_general /></_notes></annotations><documentation><input /><output /><implementation><description /></implementation></documentation></call><call id="a1" endpoint="move"><parameters><label>Move to coords</label><method>:post</method><arguments><v1>-0.001103757868795522</v1><v2>0.5382285939673974</v2><v3>0.19970459818836236</v3><v4>2.7278776980729975</v4><v5>-1.4913073869146722</v5><v6>-0.16973558927047291</v6></arguments></parameters><annotations><_generic /><_timing><_timing_weight /><_timing_avg /><explanations /></_timing><_shifting><_shifting_type>Duration</_shifting_type></_shifting><_context_data_analysis><probes /><ips /></_context_data_analysis><report><url /></report><_notes><_notes_general /></_notes></annotations><documentation><input /><output /><implementation><description /></implementation></documentation></call><call id="a2" endpoint="move"><parameters><label>Move to coords</label><method>:post</method><arguments><v1>0.00855522649343797</v1><v2>0.5675835597371611</v2><v3>0.19215518580009003</v3><v4>-2.7213050215879977</v4><v5>1.4812421246982912</v5><v6>0.1885420040686107</v6></arguments></parameters><annotations><_generic /><_timing><_timing_weight /><_timing_avg /><explanations /></_timing><_shifting><_shifting_type>Duration</_shifting_type></_shifting><_context_data_analysis><probes /><ips /></_context_data_analysis><report><url /></report><_notes><_notes_general /></_notes></annotations><documentation><input /><output /><implementation><description /></implementation></documentation></call><call id="a3" endpoint="move"><parameters><label>Move to coords</label><method>:post</method><arguments><v1>0.01659026550038291</v1><v2>0.5926148821342482</v2><v3>0.20010771788924392</v3><v4>-2.6496423477912376</v4><v5>1.4332814370468567</v5><v6>0.20761951976179457</v6></arguments></parameters><annotations><_generic /><_timing><_timing_weight /><_timing_avg /><explanations /></_timing><_shifting><_shifting_type>Duration</_shifting_type></_shifting><_context_data_analysis><probes /><ips /></_context_data_analysis><report><url /></report><_notes><_notes_general /></_notes></annotations><documentation><input /><output /><implementation><description /></implementation></documentation></call><call id="a4" endpoint="move"><parameters><label>Move to coords</label><method>:post</method><arguments><v1>0.02405196471910908</v1><v2>0.6157967783550723</v2><v3>0.21370096451112902</v3><v4>-2.5734715400965413</v4><v5>1.383063859921697</v5><v6>0.22643611268135772</v6></arguments></parameters><annotations><_generic /><_timing><_timing_weight /><_timing_avg /><explanations /></_timing><_shifting><_shifting_type>Duration</_shifting_type></_shifting><_context_data_analysis><probes /><ips /></_context_data_analysis><report><url /></report><_notes><_notes_general /></_notes></annotations><documentation><input /><output /><implementation><description /></implementation></documentation></call><call id="a5" endpoint="move"><parameters><label>Move to coords</label><method>:post</method><arguments><v1>0.016653225274144416</v1><v2>0.5926880816597321</v2><v3>0.19972789598750348</v3><v4>-2.649834230355309</v4><v5>1.43358150036719</v5><v6>0.207499190277641</v6></arguments></parameters><annotations><_generic /><_timing><_timing_weight /><_timing_avg /><explanations /></_timing><_shifting><_shifting_type>Duration</_shifting_type></_shifting><_context_data_analysis><probes /><ips /></_context_data_analysis><report><url /></report><_notes><_notes_general /></_notes></annotations><documentation><input /><output /><implementation><description /></implementation></documentation></call><call id="a6" endpoint="move"><parameters><label>Move to coords</label><method>:post</method><arguments><v1>0.008198939564588375</v1><v2>0.566383555131051</v2><v3>0.18716838063774524</v3><v4>-2.732427090261973</v4><v5>1.488665728864232</v5><v6>0.1854381066579849</v6></arguments></parameters><annotations><_generic /><_timing><_timing_weight /><_timing_avg /><explanations /></_timing><_shifting><_shifting_type>Duration</_shifting_type></_shifting><_context_data_analysis><probes /><ips /></_context_data_analysis><report><url /></report><_notes><_notes_general /></_notes></annotations><documentation><input /><output /><implementation><description /></implementation></documentation></call><call id="a7" endpoint="move"><parameters><label>Move to coords</label><method>:post</method><arguments><v1>-0.000251178694615075</v1><v2>0.5402070462908515</v2><v3>0.17782740237521674</v3><v4>2.690830001364274</v4><v5>-1.4758535119751146</v5><v6>-0.15574122959710737</v6></arguments></parameters><annotations><_generic /><_timing><_timing_weight /><_timing_avg /><explanations /></_timing><_shifting><_shifting_type>Duration</_shifting_type></_shifting><_context_data_analysis><probes /><ips /></_context_data_analysis><report><url /></report><_notes><_notes_general /></_notes></annotations><documentation><input /><output /><implementation><description /></implementation></documentation></call><call id="a8" endpoint="move"><parameters><label>Move to coords</label><method>:post</method><arguments><v1>-0.04944531060219458</v1><v2>0.5290818279140592</v2><v3>0.1751536125434369</v3><v4>2.7208711208560206</v4><v5>-1.3444199157361638</v5><v6>-0.1385649535896244</v6></arguments></parameters><annotations><_generic /><_timing><_timing_weight /><_timing_avg /><explanations /></_timing><_shifting><_shifting_type>Duration</_shifting_type></_shifting><_context_data_analysis><probes /><ips /></_context_data_analysis><report><url /></report><_notes><_notes_general /></_notes></annotations><documentation><input /><output /><implementation><description /></implementation></documentation></call><call id="a9" endpoint="move"><parameters><label>Move to coords</label><method>:post</method><arguments><v1>-0.09572392255625072</v1><v2>0.5226917362065844</v2><v3>0.17516490413947386</v3><v4>2.774064753750058</v4><v5>-1.2221079587674009</v5><v6>-0.13132739550863623</v6></arguments></parameters><annotations><_generic /><_timing><_timing_weight /><_timing_avg /><explanations /></_timing><_shifting><_shifting_type>Duration</_shifting_type></_shifting><_context_data_analysis><probes /><ips /></_context_data_analysis><report><url /></report><_notes><_notes_general /></_notes></annotations><documentation><input /><output /><implementation><description /></implementation></documentation></call><call id="a10" endpoint="move"><parameters><label>Move to coords</label><method>:post</method><arguments><v1>-0.14228663602599942</v1><v2>0.5119846734014417</v2><v3>0.175158515620175</v3><v4>2.8229125514791145</v4><v5>-1.0949068186866828</v5><v6>-0.1237919555116063</v6></arguments></parameters><annotations><_generic /><_timing><_timing_weight /><_timing_avg /><explanations /></_timing><_shifting><_shifting_type>Duration</_shifting_type></_shifting><_context_data_analysis><probes /><ips /></_context_data_analysis><report><url /></report><_notes><_notes_general /></_notes></annotations><documentation><input /><output /><implementation><description /></implementation></documentation></call><call id="a11" endpoint="move"><parameters><label>Move to coords</label><method>:post</method><arguments><v1>-0.18753423017168186</v1><v2>0.49715290220288794</v2><v3>0.17512427728585764</v3><v4>2.865937137817092</v4><v5>-0.9663148875624644</v5><v6>-0.11587255079740483</v6></arguments></parameters><annotations><_generic /><_timing><_timing_weight /><_timing_avg /><explanations /></_timing><_shifting><_shifting_type>Duration</_shifting_type></_shifting><_context_data_analysis><probes /><ips /></_context_data_analysis><report><url /></report><_notes><_notes_general /></_notes></annotations><documentation><input /><output /><implementation><description /></implementation></documentation></call><call id="a12" endpoint="move"><parameters><label>Move to coords</label><method>:post</method><arguments><v1>-0.230630479915939</v1><v2>0.47869305108042365</v2><v3>0.17509781210446956</v3><v4>2.9028452182593005</v4><v5>-0.8381707772490221</v5><v6>-0.10801576530594198</v6></arguments></parameters><annotations><_generic /><_timing><_timing_weight /><_timing_avg /><explanations /></_timing><_shifting><_shifting_type>Duration</_shifting_type></_shifting><_context_data_analysis><probes /><ips /></_context_data_analysis><report><url /></report><_notes><_notes_general /></_notes></annotations><documentation><input /><output /><implementation><description /></implementation></documentation></call><call id="a13" endpoint="move"><parameters><label>Move to coords</label><method>:post</method><arguments><v1>-0.27139217686164463</v1><v2>0.45679076537058116</v2><v3>0.17509557378516674</v3><v4>2.933843564620064</v4><v5>-0.710353693787278</v5><v6>-0.09998354508405208</v6></arguments></parameters><annotations><_generic /><_timing><_timing_weight /><_timing_avg /><explanations /></_timing><_shifting><_shifting_type>Duration</_shifting_type></_shifting><_context_data_analysis><probes /><ips /></_context_data_analysis><report><url /></report><_notes><_notes_general /></_notes></annotations><documentation><input /><output /><implementation><description /></implementation></documentation></call><call id="a14" endpoint="move"><parameters><label>Move to coords</label><method>:post</method><arguments><v1>-0.22844738811135765</v1><v2>0.47968222553694717</v2><v3>0.17496501303516726</v3><v4>2.9008924692185034</v4><v5>-0.844655674646305</v5><v6>-0.10802447648103629</v6></arguments></parameters><annotations><_generic /><_timing><_timing_weight /><_timing_avg /><explanations /></_timing><_shifting><_shifting_type>Duration</_shifting_type></_shifting><_context_data_analysis><probes /><ips /></_context_data_analysis><report><url /></report><_notes><_notes_general /></_notes></annotations><documentation><input /><output /><implementation><description /></implementation></documentation></call><call id="a15" endpoint="move"><parameters><label>Move to coords</label><method>:post</method><arguments><v1>-0.18387798566527574</v1><v2>0.4984580326434624</v2><v3>0.17496551200526833</v3><v4>2.862357009090816</v4><v5>-0.9768049871813596</v5><v6>-0.11616221000707516</v6></arguments></parameters><annotations><_generic /><_timing><_timing_weight /><_timing_avg /><explanations /></_timing><_shifting><_shifting_type>Duration</_shifting_type></_shifting><_context_data_analysis><probes /><ips /></_context_data_analysis><report><url /></report><_notes><_notes_general /></_notes></annotations><documentation><input /><output /><implementation><description /></implementation></documentation></call><call id="a16" endpoint="move"><parameters><label>Move to coords</label><method>:post</method><arguments><v1>-0.13824354387985982</v1><v2>0.5129869633351261</v2><v3>0.17495261518513133</v3><v4>2.818368839662319</v4><v5>-1.1060476510719996</v5><v6>-0.12408351733670832</v6></arguments></parameters><annotations><_generic /><_timing><_timing_weight /><_timing_avg /><explanations /></_timing><_shifting><_shifting_type>Duration</_shifting_type></_shifting><_context_data_analysis><probes /><ips /></_context_data_analysis><report><url /></report><_notes><_notes_general /></_notes></annotations><documentation><input /><output /><implementation><description /></implementation></documentation></call></description>